{
  "$schema": "https://raw.githubusercontent.com/streetsidesoftware/cspell/main/packages/cspell-types/cspell.schema.json",
  "version": "0.2",
  "language": "en",
  "words": [
    "rockbot",
    "thepopebot",
    "SRCGEEE",
    "SRCGEEE",
    "HITL",
    "bizcad",
    "PPA",
    "gpush",
    "gpush-dry",
    "gpush-log",
    "slnx",
    "hvac",
    "joserfc",
    "SPIFFE",
    "SPIRE",
    "SVID",
    "ECDH",
    "JWE",
    "JWK",
    "JOSE",
    "AKV",
    "SLSA",
    "SBOM",
    "OIDC",
    "Entra",
    "AppRole",
    "Infisical",
    "Doppler",
    "SeaweedFS",
    "BitNet",
    "FAISS",
    "CockroachDB",
    "RBAC",
    "HITL",
    "OpenClaw"
  ],
  "ignorePaths": [
    ".venv/**",
    "node_modules/**",
    "*.lock",
    "logs/**"
  ]
}
